libellula/__init__.py
libellula/libellula.py
libellula/py.typed
libellula-1.2.1.dist-info/METADATA
libellula-1.2.1.dist-info/WHEEL
libellula-1.2.1.dist-info/licenses/LICENSE
libellula-1.2.1.dist-info/RECORD
