Metadata-Version: 2.4
Name: libellula
Version: 1.2.1
Summary: humble utils
Project-URL: Repository, https://github.com/Marsella8/libellula
Author-email: Pietro <pietromax.marsella@gmail.com>
License: MIT
License-File: LICENSE
Requires-Python: >=3.13
